ckanext_vocabularies-0.0.8-py3.10-nspkg.pth
ckanext/vocabularies/__init__.py
ckanext/vocabularies/blueprints.py
ckanext/vocabularies/helpers.py
ckanext/vocabularies/logic.py
ckanext/vocabularies/plugin.py
ckanext/vocabularies/assets/webassets.yml
ckanext/vocabularies/dsc/__init__.py
ckanext/vocabularies/dsc/idsapi.py
ckanext/vocabularies/dsc/resourceapi.py
ckanext/vocabularies/dsc/subscribe.py
ckanext/vocabularies/dsc/subscriptionapi.py
ckanext/vocabularies/templates/base.html
ckanext/vocabularies/templates/scheming/form_snippets/autocomplete_dropdown.html
ckanext/vocabularies/tests/__init__.py
ckanext/vocabularies/tests/test_plugin.py
ckanext_vocabularies-0.0.8.dist-info/LICENSE
ckanext_vocabularies-0.0.8.dist-info/METADATA
ckanext_vocabularies-0.0.8.dist-info/WHEEL
ckanext_vocabularies-0.0.8.dist-info/entry_points.txt
ckanext_vocabularies-0.0.8.dist-info/namespace_packages.txt
ckanext_vocabularies-0.0.8.dist-info/top_level.txt
ckanext_vocabularies-0.0.8.dist-info/RECORD
