Metadata-Version: 2.1
Name: ckanext-vocabularies
Version: 0.0.8
Summary: Getting choices options for the scheming choise type of field, based on SKOS vocabulary served on a remote SPARQL endpoint
Home-page: https://github.com/s.karampatakis@gmail.com/ckanext-vocabularies
Author: Sotirios Karampatakis
Author-email: sotiris.karampatakis@semantic-web.com
License: AGPL
Keywords: CKAN vocabularies SKOS scheming
Classifier: Development Status :: 4 - Beta
Classifier: License :: OSI Approved :: GNU Affero General Public License v3 or later (AGPLv3+)
Classifier: Programming Language :: Python :: 2.7
License-File: LICENSE
